chreader/__init__.py
chreader/cli.py
chreader/core.py
chreader/version.py
chreader/classification/__init__.py
chreader/classification/afqmc.py
chreader/classification/tnews.py
chreader/common/__init__.py
chreader/common/exceptions.py
chreader/data/__init__.py
chreader/data/ch_dataset_reader.py
chreader/formats/__init__.py
chreader/formats/format.py
chreader/formats/json.py
chreader-0.2.1.dist-info/LICENSE
chreader-0.2.1.dist-info/METADATA
chreader-0.2.1.dist-info/WHEEL
chreader-0.2.1.dist-info/entry_points.txt
chreader-0.2.1.dist-info/top_level.txt
chreader-0.2.1.dist-info/RECORD
