Metadata-Version: 2.1
Name: chreader
Version: 0.2.1
Summary: An open-source Chinese NLP Dataset Reader library, built on allennlp & pytorch.
Home-page: https://github.com/wangyuxinwhy/chreader
Author: wangyuxin
Author-email: wangyuxinwhy@gmail.com
License: MIT
Keywords: allennlp deep learning chinese dataset reader
Platform: UNKNOWN
Classifier: Intended Audience :: Science/Research
Classifier: License :: OSI Approved :: MIT License
Classifier: Programming Language :: Python :: 3
Classifier: Topic :: Scientific/Engineering :: Artificial Intelligence
Requires-Python: >=3.6.1
Requires-Dist: allennlp
Requires-Dist: rich
Requires-Dist: click
